LICENSE
MANIFEST.in
README.rst
setup.py
emailpgp/__init__.py
emailpgp/mime/__init__.py
emailpgp/mime/multipartpgp.py