Metadata-Version: 1.2
Name: emailpgp
Version: 0.2.0
Summary: Extend Python email.mime classes to add MIME multipart/pgp-encrypted type messages.
Home-page: https://github.com/juga0/emailpgp
Author: juga
Author-email: juga@riseup.net
License: MIT
Keywords: python mime OpenPGP
Platform: UNKNOWN
Classifier: Development Status :: 3 - Alpha
Classifier: Environment :: Console
Classifier: Intended Audience :: Developers
Classifier: License :: OSI Approved :: MIT License
Classifier: Operating System :: OS Independent
Classifier: Programming Language :: Python :: 3.5
Classifier: Programming Language :: Python :: 3.6
Classifier: Topic :: System :: Networking
Requires-Python: >=3.5
